[{"TheoremString":"CollinearPoints: A, D, G","Ranking":{"Rankings":{"Symmetry":{"Ranking":0.3333333333333333,"Weight":10000.0,"Contribution":3333.333333333333},"Level":{"Ranking":0.8846153846153846,"Weight":1000.0,"Contribution":884.6153846153845},"NumberOfCyclicQuadrilaterals":{"Ranking":4.0,"Weight":-10.0,"Contribution":-40.0},"NumberOfTheorems":{"Ranking":28.0,"Weight":-1.0,"Contribution":-28.0}},"TotalRanking":4149.948717948718},"ConfigurationString":"Triangle: A, B, C\nD = PerpendicularProjectionOnLineFromPoints(A, B, C)\nE = PerpendicularProjectionOnLineFromPoints(B, A, C)\nF = PerpendicularProjectionOnLineFromPoints(C, A, B)\nG = Circumcenter(A, E, F)"},{"TheoremString":"CollinearPoints: A, D, G","Ranking":{"Rankings":{"Symmetry":{"Ranking":0.3333333333333333,"Weight":10000.0,"Contribution":3333.333333333333},"Level":{"Ranking":0.8846153846153846,"Weight":1000.0,"Contribution":884.6153846153845},"NumberOfCyclicQuadrilaterals":{"Ranking":6.0,"Weight":-10.0,"Contribution":-60.0},"NumberOfTheorems":{"Ranking":39.0,"Weight":-1.0,"Contribution":-39.0}},"TotalRanking":4118.948717948718},"ConfigurationString":"Triangle: A, B, C\nD = PerpendicularProjectionOnLineFromPoints(A, B, C)\nE = PerpendicularProjectionOnLineFromPoints(B, A, C)\nF = PerpendicularProjectionOnLineFromPoints(C, A, B)\nG = Incenter(D, E, F)"}]